flysearch/__init__.py
flysearch/api.py
flysearch/options.py
flysearch/trip.py
flysearch-0.1.3.dist-info/LICENSE
flysearch-0.1.3.dist-info/METADATA
flysearch-0.1.3.dist-info/WHEEL
flysearch-0.1.3.dist-info/top_level.txt
flysearch-0.1.3.dist-info/RECORD
