Metadata-Version: 2.1
Name: flysearch
Version: 0.1.3
Summary: Flight Search API Wrapper
Author: adiorz
Author-email: adiorz90@gmail.com
Project-URL: Source, https://github.com/Adiorz/flysearch
Project-URL: Tracker, https://github.com/Adiorz/flysearch/issues
Classifier: Programming Language :: Python :: 3
Classifier: License :: OSI Approved :: MIT License
Classifier: Operating System :: OS Independent
License-File: LICENSE
Requires-Dist: requests
